{
  "headline_theorems": [
    "Causalean.Discovery.LiNGAM.kurt",
    "Causalean.Discovery.LiNGAM.cross_fourth_cumulant_eq_sum",
    "Causalean.Discovery.LiNGAM.colSupport_of_kurtosis",
    "Causalean.Discovery.LiNGAM.ica_genPerm_relation",
    "Causalean.Discovery.LiNGAM.lingam_identifiable",
    "Causalean.Discovery.LiNGAM.lingam_identifiability_kurtosis",
    "Causalean.Discovery.LinearDisentanglement.Solution",
    "Causalean.Discovery.LinearDisentanglement.Solution.InSG",
    "Causalean.Discovery.LinearDisentanglement.IsPORQ",
    "Causalean.Discovery.LinearDisentanglement.key_identity",
    "Causalean.Discovery.LinearDisentanglement.porq_exists",
    "Causalean.Discovery.LinearDisentanglement.porq_unique",
    "Causalean.Discovery.LinearDisentanglement.rowspan_inclusion_a",
    "Causalean.Discovery.LinearDisentanglement.rowspan_inclusion_b",
    "Causalean.Discovery.LinearDisentanglement.rowspan_inclusion_c",
    "Causalean.Discovery.LinearDisentanglement.sigma_solutions",
    "Causalean.Discovery.LinearDisentanglement.disentanglement_uniqueness",
    "Causalean.Discovery.LinearDisentanglement.disentanglement_identifiability",
    "Causalean.Discovery.InvariantPrediction.EnvFamily",
    "Causalean.Discovery.InvariantPrediction.EnvFamily.Invariant",
    "Causalean.Discovery.InvariantPrediction.EnvFamily.idSet",
    "Causalean.Discovery.InvariantPrediction.EnvFamily.condDistrib_eq_mechanismKernel_of_indep",
    "Causalean.Discovery.InvariantPrediction.EnvFamily.condDistrib_target_eq_mechanismKernel",
    "Causalean.Discovery.InvariantPrediction.EnvFamily.mechanism_invariant",
    "Causalean.Discovery.InvariantPrediction.EnvFamily.mechanismKernel_cf_env_eq",
    "Causalean.Discovery.InvariantPrediction.EnvFamily.icp_sound",
    "Causalean.Discovery.InvariantPrediction.LinearGaussian.ObsSEM",
    "Causalean.Discovery.InvariantPrediction.LinearGaussian.EnvFamily",
    "Causalean.Discovery.InvariantPrediction.LinearGaussian.EnvFamily.HasShiftedSingleInterventions",
    "Causalean.Discovery.InvariantPrediction.LinearGaussian.EnvFamily.InvarianceNull",
    "Causalean.Discovery.InvariantPrediction.LinearGaussian.EnvFamily.identifiedSet",
    "Causalean.Discovery.InvariantPrediction.LinearGaussian.EnvFamily.exists_youngest_nonzero",
    "Causalean.Discovery.InvariantPrediction.LinearGaussian.EnvFamily.mem_identifiedSet",
    "Causalean.Discovery.InvariantPrediction.LinearGaussian.EnvFamily.icp_complete_linearGaussian",
    "Causalean.Discovery.InvariantPrediction.LinearGaussian.EnvFamily.icp_sound_linearGaussian",
    "Causalean.Discovery.InvariantPrediction.LinearGaussian.EnvFamily.residual_mean_shift_of_doIntervention",
    "Causalean.Discovery.InvariantPrediction.LinearGaussian.envResidual_eq_eps",
    "Causalean.Discovery.InvariantPrediction.LinearGaussian.nonDescendant_invariance",
    "Causalean.Discovery.InvariantPrediction.LinearGaussian.obsResidual_eq_eps",
    "Causalean.Discovery.InvariantPrediction.EnvFamily.paFix_eq",
    "Causalean.Discovery.InvariantPrediction.EnvFamily.paObs_mem_invariantSets",
    "Causalean.Discovery.InvariantPrediction.LinearGaussian.ObsSEM.mem_paY",
    "Causalean.Discovery.InvariantPrediction.LinearGaussian.eps_integral_zero",
    "Causalean.Discovery.LinearDisentanglement.permMat_mul_transpose"
  ],
  "reviews": [
    {
      "decl": "Causalean.Discovery.LiNGAM.kurt",
      "statement_hash": "sha256:12e3d07605ed3735cf589aca0bfdc13e4e3a851e8e5f24866f4e470dba5db32e",
      "reviewed_at_commit": "9e2f9f44814c1e475f9a1fe17e998f7fa0d5b2ad",
      "reviewer": "jytan12",
      "note": ""
    },
    {
      "decl": "Causalean.Discovery.LiNGAM.colSupport_of_kurtosis",
      "statement_hash": "sha256:0bdb8031d4bc45a7ad220c1d3eba37363c3f9ed15b0ed42828e111989a7f46fa",
      "reviewed_at_commit": "9e2f9f44814c1e475f9a1fe17e998f7fa0d5b2ad",
      "reviewer": "jytan12",
      "note": ""
    },
    {
      "decl": "Causalean.Discovery.LiNGAM.lingam_identifiable",
      "statement_hash": "sha256:c2527e2a7d77510d696a0a604a5addbd0b796126d67e808401d8cd11dbca5879",
      "reviewed_at_commit": "9e2f9f44814c1e475f9a1fe17e998f7fa0d5b2ad",
      "reviewer": "jytan12",
      "note": ""
    },
    {
      "decl": "Causalean.Discovery.LiNGAM.ica_genPerm_relation",
      "statement_hash": "sha256:e58e44fb214c43807f0fb3333cc1afdce739ecbb91ccab54bee605f70c8dd08b",
      "reviewed_at_commit": "9e2f9f44814c1e475f9a1fe17e998f7fa0d5b2ad",
      "reviewer": "jytan12",
      "note": ""
    },
    {
      "decl": "Causalean.Discovery.LiNGAM.lingam_identifiability_kurtosis",
      "statement_hash": "sha256:97106908b7fa7cc97d1f401d394bad6f64e0d5c34261c13c374b696db26b7f2f",
      "reviewed_at_commit": "9e2f9f44814c1e475f9a1fe17e998f7fa0d5b2ad",
      "reviewer": "jytan12",
      "note": ""
    },
    {
      "decl": "Causalean.Discovery.LinearDisentanglement.stdVec",
      "statement_hash": "sha256:a858c9add12d6ac265e09cb175e2cab92c271474e78ee8568c9b289d02a3f428",
      "reviewed_at_commit": "a6d3e4d31a82e00b5e22d597ba650f315418eebc",
      "reviewer": "jytan12",
      "note": ""
    },
    {
      "decl": "Causalean.Discovery.LinearDisentanglement.permMat",
      "statement_hash": "sha256:35677900ea257c30230dd7f3b04afe9df2f67310f01bce1b73bea3c33df489e8",
      "reviewed_at_commit": "a6d3e4d31a82e00b5e22d597ba650f315418eebc",
      "reviewer": "jytan12",
      "note": ""
    },
    {
      "decl": "Causalean.Discovery.LinearDisentanglement.Solution",
      "statement_hash": "sha256:dfe2a6d651fdddbb3698366c8b0c7145b349fa662bdc09244fabef80b9af2e1e",
      "reviewed_at_commit": "a6d3e4d31a82e00b5e22d597ba650f315418eebc",
      "reviewer": "jytan12",
      "note": ""
    },
    {
      "decl": "Causalean.Discovery.LinearDisentanglement.Solution.Theta0",
      "statement_hash": "sha256:9b2fdd575b90d95eefd712f1f28dec218ada0bdd95665c6ecf6b09b051025aca",
      "reviewed_at_commit": "a6d3e4d31a82e00b5e22d597ba650f315418eebc",
      "reviewer": "jytan12",
      "note": ""
    },
    {
      "decl": "Causalean.Discovery.LinearDisentanglement.Solution.Theta",
      "statement_hash": "sha256:9f329878cc78a7716c0581d0a241df8e5454cf65ed5841a4b930f2699c825b50",
      "reviewed_at_commit": "a6d3e4d31a82e00b5e22d597ba650f315418eebc",
      "reviewer": "jytan12",
      "note": ""
    },
    {
      "decl": "Causalean.Discovery.LinearDisentanglement.Solution.InSG",
      "statement_hash": "sha256:9a01acf885953a412826ae7b646484bd8b5cef19599874053259a867313333c6",
      "reviewed_at_commit": "a6d3e4d31a82e00b5e22d597ba650f315418eebc",
      "reviewer": "jytan12",
      "note": ""
    },
    {
      "decl": "Causalean.Discovery.LinearDisentanglement.Solution.pa",
      "statement_hash": "sha256:d9b2743a1d18e499a14c14eae3b6cb0773a875c772e81117f3b0ad3ccae0587c",
      "reviewed_at_commit": "a6d3e4d31a82e00b5e22d597ba650f315418eebc",
      "reviewer": "jytan12",
      "note": ""
    },
    {
      "decl": "Causalean.Discovery.LinearDisentanglement.Solution.Pa",
      "statement_hash": "sha256:d9b2743a1d18e499a14c14eae3b6cb0773a875c772e81117f3b0ad3ccae0587c",
      "reviewed_at_commit": "a6d3e4d31a82e00b5e22d597ba650f315418eebc",
      "reviewer": "jytan12",
      "note": ""
    },
    {
      "decl": "Causalean.Discovery.LinearDisentanglement.Solution.anc",
      "statement_hash": "sha256:d9b2743a1d18e499a14c14eae3b6cb0773a875c772e81117f3b0ad3ccae0587c",
      "reviewed_at_commit": "a6d3e4d31a82e00b5e22d597ba650f315418eebc",
      "reviewer": "jytan12",
      "note": ""
    },
    {
      "decl": "Causalean.Discovery.LinearDisentanglement.Solution.An",
      "statement_hash": "sha256:d9b2743a1d18e499a14c14eae3b6cb0773a875c772e81117f3b0ad3ccae0587c",
      "reviewed_at_commit": "a6d3e4d31a82e00b5e22d597ba650f315418eebc",
      "reviewer": "jytan12",
      "note": ""
    },
    {
      "decl": "Causalean.Discovery.LinearDisentanglement.Solution.prec",
      "statement_hash": "sha256:eb31adb202e9b641c7118455d05df655083288064643d860173ef19a38f45e2c",
      "reviewed_at_commit": "a6d3e4d31a82e00b5e22d597ba650f315418eebc",
      "reviewer": "jytan12",
      "note": ""
    },
    {
      "decl": "Causalean.Discovery.LinearDisentanglement.Solution.preceq",
      "statement_hash": "sha256:eb31adb202e9b641c7118455d05df655083288064643d860173ef19a38f45e2c",
      "reviewed_at_commit": "a6d3e4d31a82e00b5e22d597ba650f315418eebc",
      "reviewer": "jytan12",
      "note": ""
    },
    {
      "decl": "Causalean.Discovery.LinearDisentanglement.IsPORQ",
      "statement_hash": "sha256:e8cadd2d5ffe95ddf9820fdbae1895efb966a6fc13c180ef24961cb414d97826",
      "reviewed_at_commit": "a6d3e4d31a82e00b5e22d597ba650f315418eebc",
      "reviewer": "jytan12",
      "note": ""
    },
    {
      "decl": "Causalean.Discovery.LinearDisentanglement.porqResidual",
      "statement_hash": "sha256:5b03c81403f0fe1d46c17ca61d19e456f968315dccfb1a968f0467123d5b343a",
      "reviewed_at_commit": "a6d3e4d31a82e00b5e22d597ba650f315418eebc",
      "reviewer": "jytan12",
      "note": ""
    },
    {
      "decl": "Causalean.Discovery.LinearDisentanglement.porqAncSpan",
      "statement_hash": "sha256:c226c11df33e6f1fc643c94123a0cf01c6d35902bd7ac3d5464a3c8f36b0773d",
      "reviewed_at_commit": "a6d3e4d31a82e00b5e22d597ba650f315418eebc",
      "reviewer": "jytan12",
      "note": ""
    },
    {
      "decl": "Causalean.Discovery.LinearDisentanglement.porq_exists",
      "statement_hash": "sha256:fa0258b4e8d4989b702f54817859baaed36b33f924f777da6aef029f4eb22f8f",
      "reviewed_at_commit": "a6d3e4d31a82e00b5e22d597ba650f315418eebc",
      "reviewer": "jytan12",
      "note": ""
    },
    {
      "decl": "Causalean.Discovery.LinearDisentanglement.porq_unique",
      "statement_hash": "sha256:ff55a2089a4c071a44d17a55eadaef172bd5986e987d9503f94783a51fde869f",
      "reviewed_at_commit": "a6d3e4d31a82e00b5e22d597ba650f315418eebc",
      "reviewer": "jytan12",
      "note": ""
    },
    {
      "decl": "Causalean.Discovery.LinearDisentanglement.disentanglement_identifiability",
      "statement_hash": "sha256:e085f60dbd617d913796d76e3a931458dfb4dca070d834e5d3116b5e4d742d21",
      "reviewed_at_commit": "a6d3e4d31a82e00b5e22d597ba650f315418eebc",
      "reviewer": "jytan12",
      "note": ""
    },
    {
      "decl": "Causalean.Discovery.LinearDisentanglement.key_identity",
      "statement_hash": "sha256:ab0e126140ca77ed6604fa843f833c684e15a68e88ee5ba8cbbdb141df169a61",
      "reviewed_at_commit": "a6d3e4d31a82e00b5e22d597ba650f315418eebc",
      "reviewer": "jytan12",
      "note": ""
    },
    {
      "decl": "Causalean.Discovery.LinearDisentanglement.rowSpan",
      "statement_hash": "sha256:244962a641522b4c0839525ec1716862bc5cc4c92c5d1d15380f8403a0d97ab4",
      "reviewed_at_commit": "a6d3e4d31a82e00b5e22d597ba650f315418eebc",
      "reviewer": "jytan12",
      "note": ""
    },
    {
      "decl": "Causalean.Discovery.LinearDisentanglement.hSpan",
      "statement_hash": "sha256:8be101207fad25c0bcba41c956591c6b94b68a9bf357e1e95cfda27229eafeab",
      "reviewed_at_commit": "a6d3e4d31a82e00b5e22d597ba650f315418eebc",
      "reviewer": "jytan12",
      "note": ""
    },
    {
      "decl": "Causalean.Discovery.LinearDisentanglement.qSpan",
      "statement_hash": "sha256:721eace810bc9bcfb7070dd252b38f2ba2489bc552ba3e7b1fd18a171e162883",
      "reviewed_at_commit": "a6d3e4d31a82e00b5e22d597ba650f315418eebc",
      "reviewer": "jytan12",
      "note": ""
    },
    {
      "decl": "Causalean.Discovery.LinearDisentanglement.rowspan_inclusion_a",
      "statement_hash": "sha256:91ec92650120bb2da9c09370141dd5a85ecfa2082007eebf4d541a1ba34b8db5",
      "reviewed_at_commit": "a6d3e4d31a82e00b5e22d597ba650f315418eebc",
      "reviewer": "jytan12",
      "note": ""
    },
    {
      "decl": "Causalean.Discovery.LinearDisentanglement.rowspan_inclusion_b",
      "statement_hash": "sha256:bba17b14af333409233d9328c5091d9e475426b1e20127ef7aebe44081c5a7e6",
      "reviewed_at_commit": "a6d3e4d31a82e00b5e22d597ba650f315418eebc",
      "reviewer": "jytan12",
      "note": ""
    },
    {
      "decl": "Causalean.Discovery.LinearDisentanglement.rowspan_inclusion_c",
      "statement_hash": "sha256:b372aaa84d970e715d9ef601111d59cd40ff14ad95cbfa94430a10f379658fec",
      "reviewed_at_commit": "a6d3e4d31a82e00b5e22d597ba650f315418eebc",
      "reviewer": "jytan12",
      "note": ""
    },
    {
      "decl": "Causalean.Discovery.LinearDisentanglement.cvec",
      "statement_hash": "sha256:122eb91b88bd3101482b192dd69b05f882ce41b3c2af866082732c86a701db10",
      "reviewed_at_commit": "a6d3e4d31a82e00b5e22d597ba650f315418eebc",
      "reviewer": "jytan12",
      "note": ""
    },
    {
      "decl": "Causalean.Discovery.LinearDisentanglement.disentanglement_uniqueness",
      "statement_hash": "sha256:e085f60dbd617d913796d76e3a931458dfb4dca070d834e5d3116b5e4d742d21",
      "reviewed_at_commit": "a6d3e4d31a82e00b5e22d597ba650f315418eebc",
      "reviewer": "jytan12",
      "note": ""
    },
    {
      "decl": "Causalean.Discovery.InvariantPrediction.EnvFamily",
      "statement_hash": "sha256:392057bd179bc30055fecacd79b0a893296d5dfe49feb78c1adf906f73d1a976",
      "reviewed_at_commit": "a6d3e4d31a82e00b5e22d597ba650f315418eebc",
      "reviewer": "jytan12",
      "note": ""
    },
    {
      "decl": "Causalean.Discovery.InvariantPrediction.EnvFamily.yNode",
      "statement_hash": "sha256:46577324772d5b66b48d173a64352538a3e7db6c23fd29cfb532f2f7aa8f00cc",
      "reviewed_at_commit": "a6d3e4d31a82e00b5e22d597ba650f315418eebc",
      "reviewer": "jytan12",
      "note": ""
    },
    {
      "decl": "Causalean.Discovery.InvariantPrediction.EnvFamily.paObs",
      "statement_hash": "sha256:4e9a049a27048299c57e36a37ff17870d6f12d813b2d3115ba04c0f75e20fbca",
      "reviewed_at_commit": "a6d3e4d31a82e00b5e22d597ba650f315418eebc",
      "reviewer": "jytan12",
      "note": ""
    },
    {
      "decl": "Causalean.Discovery.InvariantPrediction.EnvFamily.paFix",
      "statement_hash": "sha256:4e9a049a27048299c57e36a37ff17870d6f12d813b2d3115ba04c0f75e20fbca",
      "reviewed_at_commit": "a6d3e4d31a82e00b5e22d597ba650f315418eebc",
      "reviewer": "jytan12",
      "note": ""
    },
    {
      "decl": "Causalean.Discovery.InvariantPrediction.EnvFamily.fixedParentVals",
      "statement_hash": "sha256:33329d59acbf1c1060b81cb463cce48af1f9f75daf546e3a522793644519b867",
      "reviewed_at_commit": "a6d3e4d31a82e00b5e22d597ba650f315418eebc",
      "reviewer": "jytan12",
      "note": ""
    },
    {
      "decl": "Causalean.Discovery.InvariantPrediction.EnvFamily.invariantSets",
      "statement_hash": "sha256:2d626dd02c5aafc4d26ecb7a50d19a0be74fb3f48c48d4ef4997caa8702192f9",
      "reviewed_at_commit": "a6d3e4d31a82e00b5e22d597ba650f315418eebc",
      "reviewer": "jytan12",
      "note": ""
    },
    {
      "decl": "Causalean.Discovery.InvariantPrediction.EnvFamily.idSet",
      "statement_hash": "sha256:f83257795541cc735b423230066d852cf7af43489e3e0980ca95c160f4d3673a",
      "reviewed_at_commit": "a6d3e4d31a82e00b5e22d597ba650f315418eebc",
      "reviewer": "jytan12",
      "note": ""
    },
    {
      "decl": "Causalean.Discovery.InvariantPrediction.EnvFamily.paLat",
      "statement_hash": "sha256:4e9a049a27048299c57e36a37ff17870d6f12d813b2d3115ba04c0f75e20fbca",
      "reviewed_at_commit": "a6d3e4d31a82e00b5e22d597ba650f315418eebc",
      "reviewer": "jytan12",
      "note": ""
    },
    {
      "decl": "Causalean.Discovery.InvariantPrediction.EnvFamily.mechanismFun",
      "statement_hash": "sha256:cf68381d680d6f7e0124ea8d0dca7783802e8bd9d3848efe739d1cd329f492ce",
      "reviewed_at_commit": "a6d3e4d31a82e00b5e22d597ba650f315418eebc",
      "reviewer": "jytan12",
      "note": ""
    },
    {
      "decl": "Causalean.Discovery.InvariantPrediction.EnvFamily.mechanismFunCf",
      "statement_hash": "sha256:e427786300671f2b85c5c849ce99c27b5421fbf6f3d25f71f51f054acd51b63b",
      "reviewed_at_commit": "a6d3e4d31a82e00b5e22d597ba650f315418eebc",
      "reviewer": "jytan12",
      "note": ""
    },
    {
      "decl": "Causalean.Discovery.InvariantPrediction.EnvFamily.condDistrib_eq_mechanismKernel_of_indep",
      "statement_hash": "sha256:3add8d01b9616f26f7f8e548ccf8beecc7078d2eb829ef06fad7bd5a4e2a1223",
      "reviewed_at_commit": "a6d3e4d31a82e00b5e22d597ba650f315418eebc",
      "reviewer": "jytan12",
      "note": ""
    },
    {
      "decl": "Causalean.Discovery.InvariantPrediction.LinearGaussian.nonDescendant_invariance",
      "statement_hash": "sha256:05ecd28662b9140a0353d3abec4d0a64f25ed18e150ab549a56074b5ba2589a2",
      "reviewed_at_commit": "a6d3e4d31a82e00b5e22d597ba650f315418eebc",
      "reviewer": "jytan12",
      "note": ""
    },
    {
      "decl": "Causalean.Discovery.InvariantPrediction.LinearGaussian.causalCoeff",
      "statement_hash": "sha256:0d7d969f6b8cea01531e0b96eefacce3ae693d9169791719b61111a1e74a3e30",
      "reviewed_at_commit": "a6d3e4d31a82e00b5e22d597ba650f315418eebc",
      "reviewer": "jytan12",
      "note": ""
    },
    {
      "decl": "Causalean.Discovery.InvariantPrediction.LinearGaussian.obsResidual_eq_eps",
      "statement_hash": "sha256:843076343b1a8c15b5210862795e909af8b964702ad03970190f9f35d12e5d51",
      "reviewed_at_commit": "a6d3e4d31a82e00b5e22d597ba650f315418eebc",
      "reviewer": "jytan12",
      "note": ""
    },
    {
      "decl": "Causalean.Discovery.InvariantPrediction.LinearGaussian.envResidual_eq_eps",
      "statement_hash": "sha256:d8a65047d1241b0554689036eb5e890ed3afac3f3ba2625306277b0c560cd106",
      "reviewed_at_commit": "a6d3e4d31a82e00b5e22d597ba650f315418eebc",
      "reviewer": "jytan12",
      "note": ""
    },
    {
      "decl": "Causalean.Discovery.InvariantPrediction.LinearGaussian.target",
      "statement_hash": "sha256:b8dcfbe1aea6a127e21680a41b669fbfeddee564792475c05a4945d7c3410691",
      "reviewed_at_commit": "a6d3e4d31a82e00b5e22d597ba650f315418eebc",
      "reviewer": "jytan12",
      "note": ""
    },
    {
      "decl": "Causalean.Discovery.InvariantPrediction.LinearGaussian.predictors",
      "statement_hash": "sha256:ee8ec80b3c0ebfd1599b545d274a8d7bcc7d262127b3c8fa24b5fb2355d6f6af",
      "reviewed_at_commit": "a6d3e4d31a82e00b5e22d597ba650f315418eebc",
      "reviewer": "jytan12",
      "note": ""
    },
    {
      "decl": "Causalean.Discovery.InvariantPrediction.LinearGaussian.ObsSEM",
      "statement_hash": "sha256:a8042440b532bb3b1accf778c3f7f48495512c66b7785425fe9a7ba0608c216d",
      "reviewed_at_commit": "a6d3e4d31a82e00b5e22d597ba650f315418eebc",
      "reviewer": "jytan12",
      "note": ""
    },
    {
      "decl": "Causalean.Discovery.InvariantPrediction.LinearGaussian.ObsSEM.paY",
      "statement_hash": "sha256:0d0cf38966f1ea71cd2ad03bcb858acd4546b78e9793170709d1d14929d83657",
      "reviewed_at_commit": "a6d3e4d31a82e00b5e22d597ba650f315418eebc",
      "reviewer": "jytan12",
      "note": ""
    },
    {
      "decl": "Causalean.Discovery.InvariantPrediction.LinearGaussian.Env",
      "statement_hash": "sha256:bfb74b41e3ad77f12a48bfcb6f46d5f200c81545296dde4fbee27e922fb78c44",
      "reviewed_at_commit": "a6d3e4d31a82e00b5e22d597ba650f315418eebc",
      "reviewer": "jytan12",
      "note": ""
    },
    {
      "decl": "Causalean.Discovery.InvariantPrediction.LinearGaussian.EnvFamily",
      "statement_hash": "sha256:a8042440b532bb3b1accf778c3f7f48495512c66b7785425fe9a7ba0608c216d",
      "reviewed_at_commit": "a6d3e4d31a82e00b5e22d597ba650f315418eebc",
      "reviewer": "jytan12",
      "note": ""
    },
    {
      "decl": "Causalean.Discovery.InvariantPrediction.LinearGaussian.EnvFamily.paY",
      "statement_hash": "sha256:ab1bf1ddcef6e7a18934d4c04ababfc5a9b8915d2d1a9f7a8f277fb0b0ff9e48",
      "reviewed_at_commit": "a6d3e4d31a82e00b5e22d597ba650f315418eebc",
      "reviewer": "jytan12",
      "note": ""
    },
    {
      "decl": "Causalean.Discovery.InvariantPrediction.LinearGaussian.SupportedOn",
      "statement_hash": "sha256:795daf27080fabc8d01d443a54894b2b18b1d79455ed6e30ada59f61b488934a",
      "reviewed_at_commit": "a6d3e4d31a82e00b5e22d597ba650f315418eebc",
      "reviewer": "jytan12",
      "note": ""
    },
    {
      "decl": "Causalean.Discovery.InvariantPrediction.LinearGaussian.obsResidual",
      "statement_hash": "sha256:f4673dc0959c5d12c5dd40ace23335a136f4fe4436db3796c03ea46207355a1b",
      "reviewed_at_commit": "a6d3e4d31a82e00b5e22d597ba650f315418eebc",
      "reviewer": "jytan12",
      "note": ""
    },
    {
      "decl": "Causalean.Discovery.InvariantPrediction.LinearGaussian.envResidual",
      "statement_hash": "sha256:f5d6c620ea08befc81285c47c777c53ff73c6a999ef92684de1efdb37134d0ae",
      "reviewed_at_commit": "a6d3e4d31a82e00b5e22d597ba650f315418eebc",
      "reviewer": "jytan12",
      "note": ""
    },
    {
      "decl": "Causalean.Discovery.InvariantPrediction.LinearGaussian.EnvFamily.InvarianceNull",
      "statement_hash": "sha256:140645adb74c4c7ed1e69e616d14546132f560311b4f68feaee65774426b56aa",
      "reviewed_at_commit": "a6d3e4d31a82e00b5e22d597ba650f315418eebc",
      "reviewer": "jytan12",
      "note": ""
    },
    {
      "decl": "Causalean.Discovery.InvariantPrediction.LinearGaussian.EnvFamily.invariantSets",
      "statement_hash": "sha256:0f45eb2f1be5f90b300f231b5e2a0239451956bf34453b0c01038c600ed4590f",
      "reviewed_at_commit": "a6d3e4d31a82e00b5e22d597ba650f315418eebc",
      "reviewer": "jytan12",
      "note": ""
    },
    {
      "decl": "Causalean.Discovery.InvariantPrediction.LinearGaussian.EnvFamily.identifiedSet",
      "statement_hash": "sha256:ab1bf1ddcef6e7a18934d4c04ababfc5a9b8915d2d1a9f7a8f277fb0b0ff9e48",
      "reviewed_at_commit": "a6d3e4d31a82e00b5e22d597ba650f315418eebc",
      "reviewer": "jytan12",
      "note": ""
    },
    {
      "decl": "Causalean.Discovery.InvariantPrediction.LinearGaussian.EnvFamily.mem_identifiedSet",
      "statement_hash": "sha256:fd5258b4aacd3a1a90079fd48ba611cff7c4e8bd8a93f1c32bef7162171ce429",
      "reviewed_at_commit": "a6d3e4d31a82e00b5e22d597ba650f315418eebc",
      "reviewer": "jytan12",
      "note": ""
    },
    {
      "decl": "Causalean.Discovery.InvariantPrediction.LinearGaussian.EnvFamily.obsMean",
      "statement_hash": "sha256:e6bbcf298550472ffff69e07b0e4da2b86fa29431bb77fef4a30f638092a750e",
      "reviewed_at_commit": "a6d3e4d31a82e00b5e22d597ba650f315418eebc",
      "reviewer": "jytan12",
      "note": ""
    },
    {
      "decl": "Causalean.Discovery.InvariantPrediction.LinearGaussian.EnvFamily.HasShiftedSingleInterventions",
      "statement_hash": "sha256:a811aa61944cb11c5ea759725cae59dd2e503a9621d61a18f21542ba9df0b455",
      "reviewed_at_commit": "a6d3e4d31a82e00b5e22d597ba650f315418eebc",
      "reviewer": "jytan12",
      "note": ""
    },
    {
      "decl": "Causalean.Discovery.InvariantPrediction.LinearGaussian.EnvFamily.ObsIntegrable",
      "statement_hash": "sha256:a811aa61944cb11c5ea759725cae59dd2e503a9621d61a18f21542ba9df0b455",
      "reviewed_at_commit": "a6d3e4d31a82e00b5e22d597ba650f315418eebc",
      "reviewer": "jytan12",
      "note": ""
    },
    {
      "decl": "Causalean.Discovery.InvariantPrediction.LinearGaussian.EnvFamily.icp_sound_linearGaussian",
      "statement_hash": "sha256:958211396a5fa11a7ba57b2a56d9d2aeeeda444634c1464946d8477d661dbabf",
      "reviewed_at_commit": "a6d3e4d31a82e00b5e22d597ba650f315418eebc",
      "reviewer": "jytan12",
      "note": ""
    },
    {
      "decl": "Causalean.Discovery.InvariantPrediction.LinearGaussian.EnvFamily.exists_youngest_nonzero",
      "statement_hash": "sha256:2cde58ccd02d8c5e46b0bbbed4e3137e427dadf0d74c8fa3f05740d4dcb1d3e8",
      "reviewed_at_commit": "a6d3e4d31a82e00b5e22d597ba650f315418eebc",
      "reviewer": "jytan12",
      "note": ""
    },
    {
      "decl": "Causalean.Discovery.InvariantPrediction.LinearGaussian.EnvFamily.residual_mean_shift_of_doIntervention",
      "statement_hash": "sha256:b307afced04b1eafc491adc98203b2a59c9bda52ef5bb5c0553359f2bf5de0e3",
      "reviewed_at_commit": "a6d3e4d31a82e00b5e22d597ba650f315418eebc",
      "reviewer": "jytan12",
      "note": ""
    },
    {
      "decl": "Causalean.Discovery.InvariantPrediction.LinearGaussian.EnvFamily.icp_complete_linearGaussian",
      "statement_hash": "sha256:1192003b641bb34e52651407f5825a4c9cd021e22d2f29deb581ca8d763d5495",
      "reviewed_at_commit": "a6d3e4d31a82e00b5e22d597ba650f315418eebc",
      "reviewer": "jytan12",
      "note": ""
    },
    {
      "decl": "Causalean.Discovery.InvariantPrediction.EnvFamily.mechanismKernel_cf_env_eq",
      "statement_hash": "sha256:24185f878ff9a3feb6a13cbe155756422a749646f5835d6529f91ebfedb3814f",
      "reviewed_at_commit": "a6d3e4d31a82e00b5e22d597ba650f315418eebc",
      "reviewer": "jytan12",
      "note": ""
    },
    {
      "decl": "Causalean.Discovery.InvariantPrediction.EnvFamily.Invariant",
      "statement_hash": "sha256:b9f1ff6640d7c8b079c6f70bb755fa180ba7d0facb25d4388d7816d197b39a4d",
      "reviewed_at_commit": "a6d3e4d31a82e00b5e22d597ba650f315418eebc",
      "reviewer": "jytan12",
      "note": ""
    },
    {
      "decl": "Causalean.Discovery.InvariantPrediction.EnvFamily.targetSet",
      "statement_hash": "sha256:61cad52858b1fe3b828454fdead2f17cd2a54e914ebb3ae9309e41632494b430",
      "reviewed_at_commit": "a6d3e4d31a82e00b5e22d597ba650f315418eebc",
      "reviewer": "jytan12",
      "note": ""
    },
    {
      "decl": "Causalean.Discovery.InvariantPrediction.EnvFamily.mechanism_invariant",
      "statement_hash": "sha256:ae44a1ca2e2a7702ab9fc67aa3ee4e0a3f6f7cac27d65e9970b2b866d5bf1878",
      "reviewed_at_commit": "a6d3e4d31a82e00b5e22d597ba650f315418eebc",
      "reviewer": "jytan12",
      "note": ""
    },
    {
      "decl": "Causalean.Discovery.InvariantPrediction.EnvFamily.icp_sound",
      "statement_hash": "sha256:16010d71165a29f4a2fda9eddaa5d435885c0afee9d1504bad4bde1b51447e1b",
      "reviewed_at_commit": "a6d3e4d31a82e00b5e22d597ba650f315418eebc",
      "reviewer": "jytan12",
      "note": ""
    },
    {
      "decl": "Causalean.Discovery.InvariantPrediction.EnvFamily.condDistrib_target_eq_mechanismKernel",
      "statement_hash": "sha256:5ae4d276ee2df0797fff52a260627d8ae5c91da422af23b6d0deaa2415f8e45b",
      "reviewed_at_commit": "a6d3e4d31a82e00b5e22d597ba650f315418eebc",
      "reviewer": "jytan12",
      "note": ""
    },
    {
      "decl": "Causalean.Discovery.LinearDisentanglement.Solution.permute",
      "statement_hash": "sha256:18874d0f4aa677050bb3490cabd72d00d0e26913e9c8811e19f075c31e6186d2",
      "reviewed_at_commit": "502b3573c8ed2e7614a1d0e106f33bba923cae8b",
      "reviewer": "jytan12",
      "note": ""
    },
    {
      "decl": "Causalean.Discovery.LinearDisentanglement.sigma_solutions",
      "statement_hash": "sha256:1bd1f1a473d949de5b355482cf664e66722268204a1b583d0e3ed8ce72987391",
      "reviewed_at_commit": "502b3573c8ed2e7614a1d0e106f33bba923cae8b",
      "reviewer": "jytan12",
      "note": ""
    },
    {
      "decl": "Causalean.Discovery.LiNGAM.cross_fourth_cumulant_eq_sum",
      "statement_hash": "sha256:afb28fd5efaa9b993d9cfac0c1ea9b8a7016a3ae1ef2c107434377b74ded5d1a",
      "reviewed_at_commit": "502b3573c8ed2e7614a1d0e106f33bba923cae8b",
      "reviewer": "jytan12",
      "note": ""
    },
    {
      "decl": "Causalean.Discovery.LinearDisentanglement.permMat_mul_transpose",
      "statement_hash": "sha256:787f2bc8374cc8feab36f70144849df36326aa5e4f2ecf9012666773c49483ed",
      "reviewed_at_commit": "b61c2be60743a2c58174ef2ee6e855429aae02b3",
      "reviewer": "jytan12",
      "note": ""
    },
    {
      "decl": "Causalean.Discovery.InvariantPrediction.EnvFamily.paFix_eq",
      "statement_hash": "sha256:01433e20d2cf21b2881eadf953b78fcf956b38b0ca533e78c3f60e36365fe446",
      "reviewed_at_commit": "b61c2be60743a2c58174ef2ee6e855429aae02b3",
      "reviewer": "jytan12",
      "note": ""
    },
    {
      "decl": "Causalean.Discovery.InvariantPrediction.EnvFamily.paObs_mem_invariantSets",
      "statement_hash": "sha256:e05c454826e8044f30504ac456b63852007225f0c98480825e2abd7bb2434327",
      "reviewed_at_commit": "b61c2be60743a2c58174ef2ee6e855429aae02b3",
      "reviewer": "jytan12",
      "note": ""
    },
    {
      "decl": "Causalean.Discovery.InvariantPrediction.LinearGaussian.eps_integral_zero",
      "statement_hash": "sha256:127f00da993af200a91aec203053bb911bdfa4f1b5cddfdd09688c62c27c9166",
      "reviewed_at_commit": "b61c2be60743a2c58174ef2ee6e855429aae02b3",
      "reviewer": "jytan12",
      "note": ""
    },
    {
      "decl": "Causalean.Discovery.InvariantPrediction.LinearGaussian.ObsSEM.mem_paY",
      "statement_hash": "sha256:a377249b64819ee3df1647f7b3927ead1244be7710ae0e353b37c78e9e9dd706",
      "reviewed_at_commit": "b61c2be60743a2c58174ef2ee6e855429aae02b3",
      "reviewer": "jytan12",
      "note": ""
    }
  ],
  "flags": [],
  "intro": "Causal discovery: LiNGAM identifiability, linear disentanglement, and invariant prediction tools for recovering structure from distributional and environment-shift information.",
  "namespace_intros": {
    "LiNGAM": "Linear non-Gaussian acyclic model identification: permutation uniqueness, generalized-permutation algebra, kurtosis-based column support, and the LiNGAM identifiability theorem.",
    "InvariantPrediction.Helpers": "Measure-theoretic and structural helper lemmas for invariant prediction, especially target-mechanism factorization and environment-invariance arguments.",
    "InvariantPrediction.LinearGaussian.Helpers": "Linear-Gaussian invariant-prediction helpers: intervention invariance, centered-noise moments, and residual algebra for soundness and completeness proofs."
  }
}
