{
  "status": "revise",
  "classification": "plan-gate",
  "perItemFindings": [
    {
      "label": "lem:dependency-graph-normal-bound",
      "verdict": "FLAG-P9",
      "one_line": "core status:\"cited\" must map to a gate_class:\"cited\" plan node (got gate=true, gate_class=gated) — re-laundering a citation"
    },
    {
      "label": "lem:dependency-graph-normal-bound",
      "verdict": "FLAG-P9",
      "one_line": "cited node must set 'source' to a cite: id"
    }
  ],
  "verbatim_critique": "The plan failed the deterministic gate (one-to-one coverage / kind / member / hyp-closure / reuse-existence / module). Fix these mechanical violations in plan.json, keeping every core node mapped exactly once:\n  - P9 @ lem:dependency-graph-normal-bound: core status:\"cited\" must map to a gate_class:\"cited\" plan node (got gate=true, gate_class=gated) — re-laundering a citation\n  - P9 @ lem:dependency-graph-normal-bound: cited node must set 'source' to a cite: id"
}
