{
  "proofs": [
    {
      "id": "lem:oracle-clipped-score-unbiased",
      "proof_tex": "Fix any deterministic $\\lambda \\in \\Lambda_n$. Under consistency and conditional ignorability, for each $d \\in \\{0,1\\}$ we have\n+\\[\n+g_d(X)=\\mathbb E[Y\\mid D=d,X]=\\mathbb E[Y(d)\\mid X]\n+\\]\n+almost surely. Therefore\n+\\[\n+\\tau=\\mathbb E[Y(1)-Y(0)]=\\mathbb E\\big[\\mathbb E[Y(1)-Y(0)\\mid X]\\big]=\\mathbb E[g_1(X)-g_0(X)].\n+\\]\n+Now condition on $X$. Since $e_\\lambda(X)$ is a function of $X$ alone,\n+\\[\n+\\mathbb E\\!\\left[\\frac{D\\{Y-g_1(X)\\}}{e_\\lambda(X)}\\Bigm|X\\right]\n+=\\frac{1}{e_\\lambda(X)}\\mathbb E\\!\\left[D\\,\\mathbb E\\big[Y-g_1(X)\\mid D,X\\big]\\Bigm|X\\right]=0,\n+\\]\n+because $\\mathbb E[Y-g_1(X)\\mid D=1,X]=0$ by the definition of $g_1$. Likewise,\n+\\[\n+\\mathbb E\\!\\left[\\frac{(1-D)\\{Y-g_0(X)\\}}{1-e(X)}\\Bigm|X\\right]=0\n+\\]\n+because $\\mathbb E[Y-g_0(X)\\mid D=0,X]=0$. Hence\n+\\[\n+\\mathbb E[\\psi_\\lambda(O;g_0,g_1,e)\\mid X]=g_1(X)-g_0(X),\n+\\]\n+and taking expectations yields\n+\\[\n+\\mathbb E_P[\\psi_\\lambda(O;g_0,g_1,e)]=\\mathbb E[g_1(X)-g_0(X)]=\\tau.\n+\\]\n+This proves exact unbiasedness of the oracle clipped score."
    },
    {
      "id": "lem:feasible-score-drift-decomposition",
      "proof_tex": "Write $\\delta_1=\\hat g_{1n}-g_1$, $\\delta_0=\\hat g_{0n}-g_0$, and keep the notation $\\hat e_\\lambda(x)=\\min\\{1-\\eta_+/2,\\max\\{\\hat e_n(x),\\lambda\\}\\}$. By cross-fitting, on each validation observation the fitted nuisance functions are measurable with respect to the training folds and are independent of the validation draw. Conditional on the training folds, they may therefore be treated as fixed functions.\n+\n+Expand the score difference:\n+\\[\n+\\hat\\psi_\\lambda-\\psi_\\lambda\n+=\\delta_1(X)\\Bigl(1-\\frac{D}{\\hat e_\\lambda(X)}\\Bigr)\n+-\\delta_0(X)\\Bigl(1-\\frac{1-D}{1-\\hat e_\\lambda(X)}\\Bigr)\n++D\\{Y-g_1(X)\\}\\Bigl(\\frac{1}{\\hat e_\\lambda(X)}-\\frac{1}{e_\\lambda(X)}\\Bigr)\n+-(1-D)\\{Y-g_0(X)\\}\\Bigl(\\frac{1}{1-\\hat e_\\lambda(X)}-\\frac{1}{1-e(X)}\\Bigr).\n+\\]\n+Taking conditional expectations given the training folds, the last two terms vanish because $\\mathbb E[Y-g_1(X)\\mid D=1,X]=0$ and $\\mathbb E[Y-g_0(X)\\mid D=0,X]=0$. Hence\n+\\[\n+P(\\hat\\psi_\\lambda-\\psi_\\lambda)\n+=P\\!\\left[\\delta_1(X)\\Bigl(1-\\frac{e(X)}{\\hat e_\\lambda(X)}\\Bigr)\\right]\n+-P\\!\\left[\\delta_0(X)\\frac{e(X)-\\hat e_\\lambda(X)}{1-\\hat e_\\lambda(X)}\\right].\n+\\]\n+\n+We bound the treated piece first. Split according to $\\{e(X)\\le \\lambda\\}$ and $\\{e(X)>\\lambda\\}$. On $\\{e\\le\\lambda\\}$ we only use $|1-e/\\hat e_\\lambda|\\le 1$, so Cauchy--Schwarz gives\n+\\[\n+\\left|P\\!\\left[\\delta_1(X)\\Bigl(1-\\frac{e(X)}{\\hat e_\\lambda(X)}\\Bigr)\\mathbf 1\\{e(X)\\le \\lambda\\}\\right]\\right|\n+\\le P(e(X)\\le \\lambda)^{1/2}\\,\\|\\delta_1\\|_{L_2(P_X)}\n+=\\pi(\\lambda)^{1/2}\\|\\delta_1\\|_{L_2(P_X)}.\n+\\]\n+On $\\{e>\\lambda\\}$ we have $e_\\lambda=e$, so\n+\\[\n+1-\\frac{e}{\\hat e_\\lambda}=\\frac{\\hat e_\\lambda-e}{\\hat e_\\lambda},\n+\\]\n+and because $\\hat e_\\lambda\\ge \\lambda$ pointwise,\n+\\[\n+\\left|1-\\frac{e}{\\hat e_\\lambda}\\right|\\le \\lambda^{-1}|\\hat e_\\lambda-e|.\n+\\]\n+The clipping map $u\\mapsto \\min\\{1-\\eta_+/2,\\max\\{u,\\lambda\\}\\}$ is $1$-Lipschitz, so $|\\hat e_\\lambda-e_\\lambda|\\le |\\hat e_n-e|$ pointwise; on $\\{e>\\lambda\\}$ we have $e_\\lambda=e$. Therefore\n+\\[\n+\\left|P\\!\\left[\\delta_1(X)\\Bigl(1-\\frac{e(X)}{\\hat e_\\lambda(X)}\\Bigr)\\mathbf 1\\{e(X)>\\lambda\\}\\right]\\right|\n+\\le \\lambda^{-1}\\|\\delta_1\\|_{L_2(P_X)}\\,\\|\\hat e_n-e\\|_{L_2(P_X)}.\n+\\]\n+\n+For the control piece, right-overlap implies $e(X)\\le 1-\\eta_+$ almost surely, and the definition of $\\hat e_\\lambda$ gives $\\hat e_\\lambda(X)\\le 1-\\eta_+/2$. Thus $1-\\hat e_\\lambda(X)\\ge \\eta_+/2$, so\n+\\[\n+\\left|\\frac{e(X)-\\hat e_\\lambda(X)}{1-\\hat e_\\lambda(X)}\\right|\n+\\le \\frac{2}{\\eta_+}|e(X)-\\hat e_\\lambda(X)|\n+\\le \\frac{2}{\\eta_+}|\\hat e_n(X)-e(X)|.\n+\\]\n+Hence\n+\\[\n+\\left|P\\!\\left[\\delta_0(X)\\frac{e(X)-\\hat e_\\lambda(X)}{1-\\hat e_\\lambda(X)}\\right]\\right|\n+\\le \\frac{2}{\\eta_+}\\|\\delta_0\\|_{L_2(P_X)}\\,\\|\\hat e_n-e\\|_{L_2(P_X)}.\n+\\]\n+\n+Combining the three displays,\n+\\[\n+|P(\\hat\\psi_\\lambda-\\psi_\\lambda)|\n+\\le \\pi(\\lambda)^{1/2}\\|\\delta_1\\|_{L_2(P_X)}\n++\\lambda^{-1}\\|\\delta_1\\|_{L_2(P_X)}\\|\\hat e_n-e\\|_{L_2(P_X)}\n++\\frac{2}{\\eta_+}\\|\\delta_0\\|_{L_2(P_X)}\\|\\hat e_n-e\\|_{L_2(P_X)}.\n+\\]\n+This is the exact drift decomposition needed for the feasible score."
    },
    {
      "id": "lem:feasible-score-fluctuation-bound",
      "proof_tex": "Continue to condition on the training folds, so that the fitted nuisance functions are fixed and independent of the validation sample. Let $\\mathbb G_n f=n^{-1}\\sum_{i=1}^n\\{f(O_i)-Pf\\}$ for the evaluation sample. Then\n+\\[\n+\\hat\\tau_\\lambda-P\\hat\\psi_\\lambda=\\mathbb G_n\\hat\\psi_\\lambda.\n+\\]\n+Using the decomposition from the previous lemma,\n+\\[\n+\\mathbb G_n\\hat\\psi_\\lambda\n+=\\mathbb G_n\\psi_\\lambda+\\mathbb G_n A_1-\\mathbb G_n A_0+\\mathbb G_n B_1-\\mathbb G_n B_0,\n+\\]\n+where\n+\\[\n+A_1(O)=\\delta_1(X)\\Bigl(1-\\frac{D}{\\hat e_\\lambda(X)}\\Bigr),\\qquad\n+A_0(O)=\\delta_0(X)\\Bigl(1-\\frac{1-D}{1-\\hat e_\\lambda(X)}\\Bigr),\n+\\]\n+\\[\n+B_1(O)=D\\{Y-g_1(X)\\}\\Bigl(\\frac{1}{\\hat e_\\lambda(X)}-\\frac{1}{e_\\lambda(X)}\\Bigr),\\qquad\n+B_0(O)=(1-D)\\{Y-g_0(X)\\}\\Bigl(\\frac{1}{1-\\hat e_\\lambda(X)}-\\frac{1}{1-e(X)}\\Bigr).\n+\\]\n+Each displayed summand is conditionally mean zero after centering by $P$.\n+\n+For the oracle term, $g_1$ and $g_0$ are square-integrable because they are assumed to be $L_2(P_X)$-estimable. Therefore\n+\\[\n+P[\\psi_\\lambda^2]\\le C_P\\{1+E[e_\\lambda(X)^{-1}]\\}\n+\\]\n+for a finite constant $C_P$ depending only on $P$, $\\sigma_1^2$, $\\sigma_0^2$, and $\\eta_+$. Indeed, the treated residual contribution satisfies\n+\\[\n+P\\left[\\frac{D\\{Y-g_1(X)\\}^2}{e_\\lambda(X)^2}\\right]\n+=E\\left[\\frac{e(X)\\,E[(Y-g_1(X))^2\\mid D=1,X]}{e_\\lambda(X)^2}\\right]\n+\\le \\sigma_1^2 E[e_\\lambda(X)^{-1}],\n+\\]\n+because $e(X)\\le e_\\lambda(X)$, and the control residual contribution is bounded by $\\eta_+^{-2}\\sigma_0^2$ since $1-e(X)\\ge \\eta_+$. Hence conditional Chebyshev yields\n+\\[\n+\\mathbb G_n\\psi_\\lambda=O_P\\!\\left(n^{-1/2}(1+E[e_\\lambda(X)^{-1}])^{1/2}\\right)\n+=O_P\\!\\left(n^{-1/2}E[e_\\lambda(X)^{-1}]^{1/2}\\right),\n+\\]\n+because $E[e_\\lambda(X)^{-1}]\\ge 1$.\n+\n+For $A_1$, use the crude pointwise bound $|1-D/\\hat e_\\lambda|\\le 1+\\lambda^{-1}\\le 2\\lambda^{-1}$. Hence\n+\\[\n+P[A_1^2]\\le 4\\lambda^{-2}\\|\\delta_1\\|_{L_2(P_X)}^2,\n+\\]\n+so\n+\\[\n+\\mathbb G_n A_1=O_P\\!\\left(n^{-1/2}\\lambda^{-1}\\|\\delta_1\\|_{L_2(P_X)}\\right).\n+\\]\n+\n+For $A_0$, right-overlap and the upper clipping imply $1-\\hat e_\\lambda\\ge \\eta_+/2$, hence\n+\\[\n+\\left|1-\\frac{1-D}{1-\\hat e_\\lambda}\\right|\\le 1+\\frac{2}{\\eta_+},\n+\\]\n+so\n+\\[\n+P[A_0^2]\\le C_{\\eta_+}\\|\\delta_0\\|_{L_2(P_X)}^2,\n+\\qquad\n+\\mathbb G_n A_0=O_P\\!\\left(n^{-1/2}\\|\\delta_0\\|_{L_2(P_X)}\\right).\n+\\]\n+\n+For $B_1$, the map $u\\mapsto 1/u$ is $\\lambda^{-2}$-Lipschitz on $[\\lambda,1]$, so\n+\\[\n+\\left|\\frac{1}{\\hat e_\\lambda}-\\frac{1}{e_\\lambda}\\right|\n+\\le \\lambda^{-2}|\\hat e_\\lambda-e_\\lambda|\n+\\le \\lambda^{-2}|\\hat e_n-e|.\n+\\]\n+Therefore, using the treated residual envelope,\n+\\[\n+P[B_1^2]\n+\\le \\sigma_1^2 E\\left[e(X)\\lambda^{-4}|\\hat e_n(X)-e(X)|^2\\right]\n+\\le \\sigma_1^2\\lambda^{-3}\\|\\hat e_n-e\\|_{L_2(P_X)}^2,\n+\\]\n+because $e(X)\\le e_\\lambda(X)$ and $e_\\lambda(X)\\ge \\lambda$. Thus\n+\\[\n+\\mathbb G_n B_1=O_P\\!\\left(n^{-1/2}\\lambda^{-3/2}\\|\\hat e_n-e\\|_{L_2(P_X)}\\right).\n+\\]\n+\n+For $B_0$, the map $u\\mapsto (1-u)^{-1}$ is Lipschitz on $(-\\infty,1-\\eta_+/2]$ with constant $4\\eta_+^{-2}$. Hence\n+\\[\n+\\left|\\frac{1}{1-\\hat e_\\lambda}-\\frac{1}{1-e}\\right|\n+\\le C_{\\eta_+}|\\hat e_n-e|,\n+\\]\n+and the control residual envelope gives\n+\\[\n+P[B_0^2]\\le C_{\\eta_+,\\sigma_0^2}\\|\\hat e_n-e\\|_{L_2(P_X)}^2,\n+\\qquad\n+\\mathbb G_n B_0=O_P\\!\\left(n^{-1/2}\\|\\hat e_n-e\\|_{L_2(P_X)}\\right).\n+\\]\n+\n+Summing the five centered pieces,\n+\\[\n+\\hat\\tau_\\lambda-P\\hat\\psi_\\lambda\n+=O_P\\!\\Bigl(n^{-1/2}\\bigl[E[e_\\lambda(X)^{-1}]^{1/2}\n++\\lambda^{-1}\\|\\delta_1\\|_{L_2(P_X)}\n++\\|\\delta_0\\|_{L_2(P_X)}\n++\\lambda^{-3/2}\\|\\hat e_n-e\\|_{L_2(P_X)}\n++\\|\\hat e_n-e\\|_{L_2(P_X)}\\bigr]\\Bigr).\n+\\]\n+This is the fluctuation bound available from the frozen assumptions."
    },
    {
      "id": "lem:corrected-clipped-upper",
      "proof_tex": "Assume the witness estimators satisfy\n+\\[\n+\\|\\hat g_{1n}-g_1\\|_{L_2(P_X)}=O_P(r_{1n}),\\qquad\n+\\|\\hat g_{0n}-g_0\\|_{L_2(P_X)}=O_P(r_{0n}),\\qquad\n+\\|\\hat e_n-e\\|_{L_2(P_X)}=O_P(r_{en}),\n+\\]\n+as required by the estimability assumptions. By the decomposition\n+\\[\n+\\hat\\tau_\\lambda-\\tau\n+=\\bigl(\\hat\\tau_\\lambda-P\\hat\\psi_\\lambda\\bigr)\n++P(\\hat\\psi_\\lambda-\\psi_\\lambda)\n++\\bigl(P\\psi_\\lambda-\\tau\\bigr),\n+\\]\n+Lemma \\texttt{lem:oracle-clipped-score-unbiased} gives $P\\psi_\\lambda-\\tau=0$. Lemma \\texttt{lem:feasible-score-drift-decomposition} gives\n+\\[\n+P(\\hat\\psi_\\lambda-\\psi_\\lambda)\n+=O_P\\bigl(\\pi(\\lambda)^{1/2}r_{1n}+\\lambda^{-1}r_{1n}r_{en}+r_{0n}r_{en}\\bigr),\n+\\]\n+where the last term absorbs the fixed factor $2/\\eta_+$. Lemma \\texttt{lem:feasible-score-fluctuation-bound} gives\n+\\[\n+\\hat\\tau_\\lambda-P\\hat\\psi_\\lambda\n+=O_P\\!\\Bigl(n^{-1/2}\\bigl[E[e_\\lambda(X)^{-1}]^{1/2}+\\lambda^{-1}r_{1n}+r_{0n}+\\lambda^{-3/2}r_{en}+r_{en}\\bigr]\\Bigr).\n+\\]\n+Combining the two displays yields\n+\\[\n+|\\hat\\tau_\\lambda-\\tau|\n+=O_P\\!\\Bigl(n^{-1/2}\\bigl[E[e_\\lambda(X)^{-1}]^{1/2}+\\lambda^{-1}r_{1n}+r_{0n}+\\lambda^{-3/2}r_{en}+r_{en}\\bigr]\n++\\pi(\\lambda)^{1/2}r_{1n}+\\lambda^{-1}r_{1n}r_{en}+r_{0n}r_{en}\\Bigr).\n+\\]\n+This is a valid upper envelope under the frozen assumptions. It is strictly weaker than the target envelope $U_n(\\lambda)$ because the target omits the displayed stochastic terms coming from the feasible estimated denominators."
    }
  ],
  "added_lemmas": [
    {
      "id": "lem:oracle-clipped-score-unbiased",
      "kind": "lemma",
      "statement": "For every deterministic lambda in Lambda_n and every law P satisfying ass:consistency and ass:ignorability, E_P[psi_lambda(O; g_0, g_1, e)] = tau.",
      "depends_on": [
        "ass:consistency",
        "ass:ignorability",
        "def:true-clipped-propensity",
        "def:oracle-clipped-score"
      ],
      "status": "proved",
      "proof_tex": "Fix any deterministic $\\lambda \\in \\Lambda_n$. Under consistency and conditional ignorability, for each $d \\in \\{0,1\\}$ we have\n+\\[\n+g_d(X)=\\mathbb E[Y\\mid D=d,X]=\\mathbb E[Y(d)\\mid X]\n+\\]\n+almost surely. Therefore\n+\\[\n+\\tau=\\mathbb E[Y(1)-Y(0)]=\\mathbb E\\big[\\mathbb E[Y(1)-Y(0)\\mid X]\\big]=\\mathbb E[g_1(X)-g_0(X)].\n+\\]\n+Now condition on $X$. Since $e_\\lambda(X)$ is a function of $X$ alone,\n+\\[\n+\\mathbb E\\!\\left[\\frac{D\\{Y-g_1(X)\\}}{e_\\lambda(X)}\\Bigm|X\\right]\n+=\\frac{1}{e_\\lambda(X)}\\mathbb E\\!\\left[D\\,\\mathbb E\\big[Y-g_1(X)\\mid D,X\\big]\\Bigm|X\\right]=0,\n+\\]\n+because $\\mathbb E[Y-g_1(X)\\mid D=1,X]=0$ by the definition of $g_1$. Likewise,\n+\\[\n+\\mathbb E\\!\\left[\\frac{(1-D)\\{Y-g_0(X)\\}}{1-e(X)}\\Bigm|X\\right]=0\n+\\]\n+because $\\mathbb E[Y-g_0(X)\\mid D=0,X]=0$. Hence\n+\\[\n+\\mathbb E[\\psi_\\lambda(O;g_0,g_1,e)\\mid X]=g_1(X)-g_0(X),\n+\\]\n+and taking expectations yields\n+\\[\n+\\mathbb E_P[\\psi_\\lambda(O;g_0,g_1,e)]=\\mathbb E[g_1(X)-g_0(X)]=\\tau.\n+\\]\n+This proves exact unbiasedness of the oracle clipped score."
    },
    {
      "id": "lem:feasible-score-drift-decomposition",
      "kind": "lemma",
      "statement": "Let delta_1 = hat_g_1n - g_1 and delta_0 = hat_g_0n - g_0. Conditional on the training folds used to produce the cross-fitted nuisance estimates, P(hat_psi_lambda - psi_lambda) equals the sum of the treated and control regression drift terms, and it obeys the bound |P(hat_psi_lambda - psi_lambda)| <= pi(lambda)^(1/2) ||delta_1||_{L2(P_X)} + lambda^(-1) ||delta_1||_{L2(P_X)} ||hat_e_n - e||_{L2(P_X)} + (2 / eta_plus) ||delta_0||_{L2(P_X)} ||hat_e_n - e||_{L2(P_X)}.",
      "depends_on": [
        "ass:right-overlap",
        "def:estimated-clipped-propensity",
        "def:oracle-clipped-score",
        "def:plugin-score",
        "def:tail-mass-functional"
      ],
      "status": "proved",
      "proof_tex": "Write $\\delta_1=\\hat g_{1n}-g_1$, $\\delta_0=\\hat g_{0n}-g_0$, and keep the notation $\\hat e_\\lambda(x)=\\min\\{1-\\eta_+/2,\\max\\{\\hat e_n(x),\\lambda\\}\\}$. By cross-fitting, on each validation observation the fitted nuisance functions are measurable with respect to the training folds and are independent of the validation draw. Conditional on the training folds, they may therefore be treated as fixed functions.\n+\n+Expand the score difference:\n+\\[\n+\\hat\\psi_\\lambda-\\psi_\\lambda\n+=\\delta_1(X)\\Bigl(1-\\frac{D}{\\hat e_\\lambda(X)}\\Bigr)\n+-\\delta_0(X)\\Bigl(1-\\frac{1-D}{1-\\hat e_\\lambda(X)}\\Bigr)\n++D\\{Y-g_1(X)\\}\\Bigl(\\frac{1}{\\hat e_\\lambda(X)}-\\frac{1}{e_\\lambda(X)}\\Bigr)\n+-(1-D)\\{Y-g_0(X)\\}\\Bigl(\\frac{1}{1-\\hat e_\\lambda(X)}-\\frac{1}{1-e(X)}\\Bigr).\n+\\]\n+Taking conditional expectations given the training folds, the last two terms vanish because $\\mathbb E[Y-g_1(X)\\mid D=1,X]=0$ and $\\mathbb E[Y-g_0(X)\\mid D=0,X]=0$. Hence\n+\\[\n+P(\\hat\\psi_\\lambda-\\psi_\\lambda)\n+=P\\!\\left[\\delta_1(X)\\Bigl(1-\\frac{e(X)}{\\hat e_\\lambda(X)}\\Bigr)\\right]\n+-P\\!\\left[\\delta_0(X)\\frac{e(X)-\\hat e_\\lambda(X)}{1-\\hat e_\\lambda(X)}\\right].\n+\\]\n+\n+We bound the treated piece first. Split according to $\\{e(X)\\le \\lambda\\}$ and $\\{e(X)>\\lambda\\}$. On $\\{e\\le\\lambda\\}$ we only use $|1-e/\\hat e_\\lambda|\\le 1$, so Cauchy--Schwarz gives\n+\\[\n+\\left|P\\!\\left[\\delta_1(X)\\Bigl(1-\\frac{e(X)}{\\hat e_\\lambda(X)}\\Bigr)\\mathbf 1\\{e(X)\\le \\lambda\\}\\right]\\right|\n+\\le P(e(X)\\le \\lambda)^{1/2}\\,\\|\\delta_1\\|_{L_2(P_X)}\n+=\\pi(\\lambda)^{1/2}\\|\\delta_1\\|_{L_2(P_X)}.\n+\\]\n+On $\\{e>\\lambda\\}$ we have $e_\\lambda=e$, so\n+\\[\n+1-\\frac{e}{\\hat e_\\lambda}=\\frac{\\hat e_\\lambda-e}{\\hat e_\\lambda},\n+\\]\n+and because $\\hat e_\\lambda\\ge \\lambda$ pointwise,\n+\\[\n+\\left|1-\\frac{e}{\\hat e_\\lambda}\\right|\\le \\lambda^{-1}|\\hat e_\\lambda-e|.\n+\\]\n+The clipping map $u\\mapsto \\min\\{1-\\eta_+/2,\\max\\{u,\\lambda\\}\\}$ is $1$-Lipschitz, so $|\\hat e_\\lambda-e_\\lambda|\\le |\\hat e_n-e|$ pointwise; on $\\{e>\\lambda\\}$ we have $e_\\lambda=e$. Therefore\n+\\[\n+\\left|P\\!\\left[\\delta_1(X)\\Bigl(1-\\frac{e(X)}{\\hat e_\\lambda(X)}\\Bigr)\\mathbf 1\\{e(X)>\\lambda\\}\\right]\\right|\n+\\le \\lambda^{-1}\\|\\delta_1\\|_{L_2(P_X)}\\,\\|\\hat e_n-e\\|_{L_2(P_X)}.\n+\\]\n+\n+For the control piece, right-overlap implies $e(X)\\le 1-\\eta_+$ almost surely, and the definition of $\\hat e_\\lambda$ gives $\\hat e_\\lambda(X)\\le 1-\\eta_+/2$. Thus $1-\\hat e_\\lambda(X)\\ge \\eta_+/2$, so\n+\\[\n+\\left|\\frac{e(X)-\\hat e_\\lambda(X)}{1-\\hat e_\\lambda(X)}\\right|\n+\\le \\frac{2}{\\eta_+}|e(X)-\\hat e_\\lambda(X)|\n+\\le \\frac{2}{\\eta_+}|\\hat e_n(X)-e(X)|.\n+\\]\n+Hence\n+\\[\n+\\left|P\\!\\left[\\delta_0(X)\\frac{e(X)-\\hat e_\\lambda(X)}{1-\\hat e_\\lambda(X)}\\right]\\right|\n+\\le \\frac{2}{\\eta_+}\\|\\delta_0\\|_{L_2(P_X)}\\,\\|\\hat e_n-e\\|_{L_2(P_X)}.\n+\\]\n+\n+Combining the three displays,\n+\\[\n+|P(\\hat\\psi_\\lambda-\\psi_\\lambda)|\n+\\le \\pi(\\lambda)^{1/2}\\|\\delta_1\\|_{L_2(P_X)}\n++\\lambda^{-1}\\|\\delta_1\\|_{L_2(P_X)}\\|\\hat e_n-e\\|_{L_2(P_X)}\n++\\frac{2}{\\eta_+}\\|\\delta_0\\|_{L_2(P_X)}\\|\\hat e_n-e\\|_{L_2(P_X)}.\n+\\]\n+This is the exact drift decomposition needed for the feasible score."
    },
    {
      "id": "lem:feasible-score-fluctuation-bound",
      "kind": "lemma",
      "statement": "Conditional on the training folds used for cross-fitting, the evaluation-sample fluctuation of the feasible score obeys hat_tau_lambda - P hat_psi_lambda = O_P(n^(-1/2) [ E[e_lambda(X)^(-1)]^(1/2) + lambda^(-1) ||hat_g_1n - g_1||_{L2(P_X)} + ||hat_g_0n - g_0||_{L2(P_X)} + lambda^(-3/2) ||hat_e_n - e||_{L2(P_X)} + ||hat_e_n - e||_{L2(P_X)} ]).",
      "depends_on": [
        "ass:iid",
        "ass:right-overlap",
        "ass:resid-treated",
        "ass:resid-control",
        "def:true-clipped-propensity",
        "def:estimated-clipped-propensity",
        "def:oracle-clipped-score",
        "def:plugin-score",
        "def:crossfit-estimator"
      ],
      "status": "proved",
      "proof_tex": "Continue to condition on the training folds, so that the fitted nuisance functions are fixed and independent of the validation sample. Let $\\mathbb G_n f=n^{-1}\\sum_{i=1}^n\\{f(O_i)-Pf\\}$ for the evaluation sample. Then\n+\\[\n+\\hat\\tau_\\lambda-P\\hat\\psi_\\lambda=\\mathbb G_n\\hat\\psi_\\lambda.\n+\\]\n+Using the decomposition from the previous lemma,\n+\\[\n+\\mathbb G_n\\hat\\psi_\\lambda\n+=\\mathbb G_n\\psi_\\lambda+\\mathbb G_n A_1-\\mathbb G_n A_0+\\mathbb G_n B_1-\\mathbb G_n B_0,\n+\\]\n+where\n+\\[\n+A_1(O)=\\delta_1(X)\\Bigl(1-\\frac{D}{\\hat e_\\lambda(X)}\\Bigr),\\qquad\n+A_0(O)=\\delta_0(X)\\Bigl(1-\\frac{1-D}{1-\\hat e_\\lambda(X)}\\Bigr),\n+\\]\n+\\[\n+B_1(O)=D\\{Y-g_1(X)\\}\\Bigl(\\frac{1}{\\hat e_\\lambda(X)}-\\frac{1}{e_\\lambda(X)}\\Bigr),\\qquad\n+B_0(O)=(1-D)\\{Y-g_0(X)\\}\\Bigl(\\frac{1}{1-\\hat e_\\lambda(X)}-\\frac{1}{1-e(X)}\\Bigr).\n+\\]\n+Each displayed summand is conditionally mean zero after centering by $P$.\n+\n+For the oracle term, $g_1$ and $g_0$ are square-integrable because they are assumed to be $L_2(P_X)$-estimable. Therefore\n+\\[\n+P[\\psi_\\lambda^2]\\le C_P\\{1+E[e_\\lambda(X)^{-1}]\\}\n+\\]\n+for a finite constant $C_P$ depending only on $P$, $\\sigma_1^2$, $\\sigma_0^2$, and $\\eta_+$. Indeed, the treated residual contribution satisfies\n+\\[\n+P\\left[\\frac{D\\{Y-g_1(X)\\}^2}{e_\\lambda(X)^2}\\right]\n+=E\\left[\\frac{e(X)\\,E[(Y-g_1(X))^2\\mid D=1,X]}{e_\\lambda(X)^2}\\right]\n+\\le \\sigma_1^2 E[e_\\lambda(X)^{-1}],\n+\\]\n+because $e(X)\\le e_\\lambda(X)$, and the control residual contribution is bounded by $\\eta_+^{-2}\\sigma_0^2$ since $1-e(X)\\ge \\eta_+$. Hence conditional Chebyshev yields\n+\\[\n+\\mathbb G_n\\psi_\\lambda=O_P\\!\\left(n^{-1/2}(1+E[e_\\lambda(X)^{-1}])^{1/2}\\right)\n+=O_P\\!\\left(n^{-1/2}E[e_\\lambda(X)^{-1}]^{1/2}\\right),\n+\\]\n+because $E[e_\\lambda(X)^{-1}]\\ge 1$.\n+\n+For $A_1$, use the crude pointwise bound $|1-D/\\hat e_\\lambda|\\le 1+\\lambda^{-1}\\le 2\\lambda^{-1}$. Hence\n+\\[\n+P[A_1^2]\\le 4\\lambda^{-2}\\|\\delta_1\\|_{L_2(P_X)}^2,\n+\\]\n+so\n+\\[\n+\\mathbb G_n A_1=O_P\\!\\left(n^{-1/2}\\lambda^{-1}\\|\\delta_1\\|_{L_2(P_X)}\\right).\n+\\]\n+\n+For $A_0$, right-overlap and the upper clipping imply $1-\\hat e_\\lambda\\ge \\eta_+/2$, hence\n+\\[\n+\\left|1-\\frac{1-D}{1-\\hat e_\\lambda}\\right|\\le 1+\\frac{2}{\\eta_+},\n+\\]\n+so\n+\\[\n+P[A_0^2]\\le C_{\\eta_+}\\|\\delta_0\\|_{L_2(P_X)}^2,\n+\\qquad\n+\\mathbb G_n A_0=O_P\\!\\left(n^{-1/2}\\|\\delta_0\\|_{L_2(P_X)}\\right).\n+\\]\n+\n+For $B_1$, the map $u\\mapsto 1/u$ is $\\lambda^{-2}$-Lipschitz on $[\\lambda,1]$, so\n+\\[\n+\\left|\\frac{1}{\\hat e_\\lambda}-\\frac{1}{e_\\lambda}\\right|\n+\\le \\lambda^{-2}|\\hat e_\\lambda-e_\\lambda|\n+\\le \\lambda^{-2}|\\hat e_n-e|.\n+\\]\n+Therefore, using the treated residual envelope,\n+\\[\n+P[B_1^2]\n+\\le \\sigma_1^2 E\\left[e(X)\\lambda^{-4}|\\hat e_n(X)-e(X)|^2\\right]\n+\\le \\sigma_1^2\\lambda^{-3}\\|\\hat e_n-e\\|_{L_2(P_X)}^2,\n+\\]\n+because $e(X)\\le e_\\lambda(X)$ and $e_\\lambda(X)\\ge \\lambda$. Thus\n+\\[\n+\\mathbb G_n B_1=O_P\\!\\left(n^{-1/2}\\lambda^{-3/2}\\|\\hat e_n-e\\|_{L_2(P_X)}\\right).\n+\\]\n+\n+For $B_0$, the map $u\\mapsto (1-u)^{-1}$ is Lipschitz on $(-\\infty,1-\\eta_+/2]$ with constant $4\\eta_+^{-2}$. Hence\n+\\[\n+\\left|\\frac{1}{1-\\hat e_\\lambda}-\\frac{1}{1-e}\\right|\n+\\le C_{\\eta_+}|\\hat e_n-e|,\n+\\]\n+and the control residual envelope gives\n+\\[\n+P[B_0^2]\\le C_{\\eta_+,\\sigma_0^2}\\|\\hat e_n-e\\|_{L_2(P_X)}^2,\n+\\qquad\n+\\mathbb G_n B_0=O_P\\!\\left(n^{-1/2}\\|\\hat e_n-e\\|_{L_2(P_X)}\\right).\n+\\]\n+\n+Summing the five centered pieces,\n+\\[\n+\\hat\\tau_\\lambda-P\\hat\\psi_\\lambda\n+=O_P\\!\\Bigl(n^{-1/2}\\bigl[E[e_\\lambda(X)^{-1}]^{1/2}\n++\\lambda^{-1}\\|\\delta_1\\|_{L_2(P_X)}\n++\\|\\delta_0\\|_{L_2(P_X)}\n++\\lambda^{-3/2}\\|\\hat e_n-e\\|_{L_2(P_X)}\n++\\|\\hat e_n-e\\|_{L_2(P_X)}\\bigr]\\Bigr).\n+\\]\n+This is the fluctuation bound available from the frozen assumptions."
    },
    {
      "id": "lem:corrected-clipped-upper",
      "kind": "lemma",
      "statement": "Under the witness-rate hypotheses in ass:estimable-g1, ass:estimable-g0, and ass:estimable-e, and for every deterministic lambda in Lambda_n, the feasible cross-fitted estimator satisfies |hat_tau_lambda - tau| = O_P( n^(-1/2) [ E[e_lambda(X)^(-1)]^(1/2) + lambda^(-1) r_1n + r_0n + lambda^(-3/2) r_en + r_en ] + pi(lambda)^(1/2) r_1n + lambda^(-1) r_1n r_en + r_0n r_en ).",
      "depends_on": [
        "ass:estimable-g1",
        "ass:estimable-g0",
        "ass:estimable-e",
        "lem:oracle-clipped-score-unbiased",
        "lem:feasible-score-drift-decomposition",
        "lem:feasible-score-fluctuation-bound"
      ],
      "status": "proved",
      "proof_tex": "Assume the witness estimators satisfy\n+\\[\n+\\|\\hat g_{1n}-g_1\\|_{L_2(P_X)}=O_P(r_{1n}),\\qquad\n+\\|\\hat g_{0n}-g_0\\|_{L_2(P_X)}=O_P(r_{0n}),\\qquad\n+\\|\\hat e_n-e\\|_{L_2(P_X)}=O_P(r_{en}),\n+\\]\n+as required by the estimability assumptions. By the decomposition\n+\\[\n+\\hat\\tau_\\lambda-\\tau\n+=\\bigl(\\hat\\tau_\\lambda-P\\hat\\psi_\\lambda\\bigr)\n++P(\\hat\\psi_\\lambda-\\psi_\\lambda)\n++\\bigl(P\\psi_\\lambda-\\tau\\bigr),\n+\\]\n+Lemma \\texttt{lem:oracle-clipped-score-unbiased} gives $P\\psi_\\lambda-\\tau=0$. Lemma \\texttt{lem:feasible-score-drift-decomposition} gives\n+\\[\n+P(\\hat\\psi_\\lambda-\\psi_\\lambda)\n+=O_P\\bigl(\\pi(\\lambda)^{1/2}r_{1n}+\\lambda^{-1}r_{1n}r_{en}+r_{0n}r_{en}\\bigr),\n+\\]\n+where the last term absorbs the fixed factor $2/\\eta_+$. Lemma \\texttt{lem:feasible-score-fluctuation-bound} gives\n+\\[\n+\\hat\\tau_\\lambda-P\\hat\\psi_\\lambda\n+=O_P\\!\\Bigl(n^{-1/2}\\bigl[E[e_\\lambda(X)^{-1}]^{1/2}+\\lambda^{-1}r_{1n}+r_{0n}+\\lambda^{-3/2}r_{en}+r_{en}\\bigr]\\Bigr).\n+\\]\n+Combining the two displays yields\n+\\[\n+|\\hat\\tau_\\lambda-\\tau|\n+=O_P\\!\\Bigl(n^{-1/2}\\bigl[E[e_\\lambda(X)^{-1}]^{1/2}+\\lambda^{-1}r_{1n}+r_{0n}+\\lambda^{-3/2}r_{en}+r_{en}\\bigr]\n++\\pi(\\lambda)^{1/2}r_{1n}+\\lambda^{-1}r_{1n}r_{en}+r_{0n}r_{en}\\Bigr).\n+\\]\n+This is a valid upper envelope under the frozen assumptions. It is strictly weaker than the target envelope $U_n(\\lambda)$ because the target omits the displayed stochastic terms coming from the feasible estimated denominators."
    }
  ],
  "proposed_statement_changes": [
    {
      "id": "thm:clipped-upper",
      "current": "Choose cross-fitted witness estimators hat_g_1n, hat_g_0n, and hat_e_n attaining the rates in ass:estimable-g1, ass:estimable-g0, and ass:estimable-e. Then for every law P satisfying ass:consistency, ass:ignorability, ass:right-overlap, ass:resid-treated, ass:resid-control, ass:estimable-g1, ass:estimable-g0, and ass:estimable-e, and in particular for every P in W_n(kappa, r_0n, r_1n, r_en) or P in W_n^reg(r_0n, r_1n, r_en), and every deterministic lambda in Lambda_n, E_P[psi_lambda(O; g_0, g_1, e)] = tau and |hat_tau_lambda - tau| = O_P(U_n(lambda)).",
      "proposed": "Choose cross-fitted witness estimators hat_g_1n, hat_g_0n, and hat_e_n attaining the rates in ass:estimable-g1, ass:estimable-g0, and ass:estimable-e. Then for every law P satisfying ass:consistency, ass:ignorability, ass:right-overlap, ass:resid-treated, ass:resid-control, ass:estimable-g1, ass:estimable-g0, and ass:estimable-e, and in particular for every P in W_n(kappa, r_0n, r_1n, r_en) or P in W_n^reg(r_0n, r_1n, r_en), and every deterministic lambda in Lambda_n, E_P[psi_lambda(O; g_0, g_1, e)] = tau and |hat_tau_lambda - tau| = O_P( n^(-1/2) [ E[e_lambda(X)^(-1)]^(1/2) + lambda^(-1) r_1n + r_0n + lambda^(-3/2) r_en + r_en ] + pi(lambda)^(1/2) r_1n + lambda^(-1) r_1n r_en + r_0n r_en ).",
      "reason": "The exact unbiasedness statement is provable, but the displayed envelope U_n(lambda) is too small under the frozen assumptions. Once the feasible score uses the estimated clipped denominator hat_e_lambda inside inverse weights, the evaluation-sample fluctuation contains extra terms that are not controlled by U_n(lambda) from only L2(P_X) nuisance rates. In the proof decomposition, the treated plug-in term contributes a centered fluctuation of order n^(-1/2) lambda^(-1) ||hat_g_1n-g_1||_{L2(P_X)}, and the treated denominator-error residual contributes a centered fluctuation of order n^(-1/2) lambda^(-3/2) ||hat_e_n-e||_{L2(P_X)}. These terms do not collapse to pi(lambda)^(1/2) r_1n + lambda^(-1) r_1n r_en without additional weighted-norm, relative-error, or high-probability stabilization assumptions that are absent from the frozen core. The proposed statement is the honest upper bound obtainable from the declared dependencies.",
      "direction": "narrow"
    }
  ]
}
